nntoolbox/__init__.py
nntoolbox/learner.py
nntoolbox/callbacks/__init__.py
nntoolbox/callbacks/bptt.py
nntoolbox/callbacks/bs_scheduler.py
nntoolbox/callbacks/callbacks.py
nntoolbox/callbacks/checkpoint.py
nntoolbox/callbacks/colab.py
nntoolbox/callbacks/debug.py
nntoolbox/callbacks/device.py
nntoolbox/callbacks/fge.py
nntoolbox/callbacks/gradient.py
nntoolbox/callbacks/logger.py
nntoolbox/callbacks/lookahead.py
nntoolbox/callbacks/lr_scheduler.py
nntoolbox/callbacks/mixed_precision.py
nntoolbox/callbacks/mixup.py
nntoolbox/callbacks/nan.py
nntoolbox/callbacks/progress_bar.py
nntoolbox/callbacks/regularization.py
nntoolbox/callbacks/resizing.py
nntoolbox/callbacks/swa.py
nntoolbox/callbacks/transfer.py
nntoolbox/callbacks/warmup.py
nntoolbox/components/__init__.py
nntoolbox/components/activation.py
nntoolbox/components/components.py
nntoolbox/components/dndf.py
nntoolbox/components/kernel.py
nntoolbox/components/maxout.py
nntoolbox/components/merge.py
nntoolbox/components/mixture.py
nntoolbox/components/moe.py
nntoolbox/components/pool.py
nntoolbox/components/rbf.py
nntoolbox/components/regularization.py
nntoolbox/components/self_normalizing.py
nntoolbox/components/shunting.py
nntoolbox/ensembler/__init__.py
nntoolbox/ensembler/cv.py
nntoolbox/graph/__init__.py
nntoolbox/graph/utils.py
nntoolbox/graph/components/__init__.py
nntoolbox/graph/components/layers.py
nntoolbox/graph/learner/__init__.py
nntoolbox/graph/learner/node_classifier.py
nntoolbox/graph/models/__init__.py
nntoolbox/graph/models/graph_conv_net.py
nntoolbox/hooks/__init__.py
nntoolbox/hooks/hooks.py
nntoolbox/hooks/inputs.py
nntoolbox/hooks/io.py
nntoolbox/hooks/stats.py
nntoolbox/hooks/utils.py
nntoolbox/init/__init__.py
nntoolbox/init/lsuv.py
nntoolbox/init/normal.py
nntoolbox/init/uniform.py
nntoolbox/losses/__init__.py
nntoolbox/losses/losses.py
nntoolbox/losses/moe.py
nntoolbox/losses/pinball.py
nntoolbox/losses/smooth.py
nntoolbox/metrics/__init__.py
nntoolbox/metrics/classification.py
nn_toolbox-0.1.4.dist-info/LICENSE
nn_toolbox-0.1.4.dist-info/METADATA
nn_toolbox-0.1.4.dist-info/WHEEL
nn_toolbox-0.1.4.dist-info/top_level.txt
nn_toolbox-0.1.4.dist-info/RECORD
